Workbook

Sheet Farmacias
A1: NOMBRE FARMACIA | B1: CIUDAD | C1: ZONA | D1: PRIORIDAD | E1: EMPLEADOS | F1: ESTADO DEL PROCESO | G1: ESTADO DEL CONTACTO | H1: TELEFONO | I1: EMAIL | J1: ULTIMA INTERACCION | K1: PROXIMA ACCION | L1: RESULTADO ULTIMO COTACTO | M1: NOTAS
A2: PARRA ASTORGANO, Mª DOLORES | B2: VALLADOLID | C2: ARTURO EYRIES | D2: BAJA | E2: 46240 | F2: Prospecto | G2: No contactado | H2: 663 081 209 | I2: info@farmaciaarturoeyries.es
A3: TEJEDOR TOQUERO, MARÍA TERESA | B3: VALLADOLID | C3: ARTURO EYRIES | D3: MEDIA | E3: 1 | F3: Prospecto | G3: No contactado | H3: 983 471 881 | I3: farmaciatejedortoquero@gmail.com
A4: RODRÍGUEZ CARRASCAL, JAVIER | B4: VALLADOLID | C4: ARTURO EYRIES | F4: Prospecto | G4: No contactado | H4: 983 23 61 14
A5: HERRERO VACA, MARÍA | B5: VALLADOLID | C5: ARTURO EYRIES | F5: Prospecto | G5: No contactado | H5: 983 231 098 | I5: mariaherrerovaca@gmail.com
A6: GARCÍA VELASCO, ROSA Mª | B6: VALLADOLID | C6: ARTURO EYRIES | D6: BAJA | E6: 46083 | F6: Prospecto | G6: No contactado | H6: 983 23 36 92
A7: SERRANO PLAZA, Mª LUISA | B7: VALLADOLID | C7: ARTURO EYRIES | D7: ALTA | F7: Prospecto | G7: No contactado | H7: 983 233 572 | I7: marialuisaserrano@redfarma.org
A8: ESCUDERO DÍEZ, MARIA LUISA | B8: VALLADOLID | C8: ARTURO EYRIES | D8: ALTA | F8: Prospecto | G8: No contactado | H8: 983 66 51 11
A9: COLMENERO DÍEZ, MARIA AUXILIADORA | B9: VALLADOLID | C9: ARTURO EYRIES | D9: BAJA | E9: 46114 | F9: Prospecto | G9: No contactado
A10: VIDAL CORCOBA, ROSARIO SANZ VIDAL, MIGUEL ÁNGEL | B10: VALLADOLID | C10: BARRIO ESPAÑA | F10: Prospecto | G10: No contactado
A11: CALZÓN DUEÑAS, LAURA | B11: VALLADOLID | C11: BARRIO ESPAÑA | F11: Prospecto | G11: No contactado
A12: PÉREZ AMPUDIA, Mª DEL MILAGRO | B12: VALLADOLID | C12: CAMPO GRANDE | F12: Prospecto | G12: No contactado
A13: RODRÍGUEZ BLANCO, EMMA | B13: VALLADOLID | C13: CAMPO GRANDE | D13: MEDIA | E13: 46054 | F13: Prospecto | G13: No contactado
A14: LÓPEZ ESCORIAL, CRISTINA | B14: VALLADOLID | C14: CAMPO GRANDE | F14: Prospecto | G14: No contactado
A15: RUIZ ALONSO, JESÚS ÁNGEL RUIZ RAMOS, JAVIER | B15: VALLADOLID | C15: CAMPO GRANDE | F15: Prospecto | G15: No contactado
A16: SANABRIA MURCIEGO, JOSÉ MIGUEL | B16: VALLADOLID | C16: CAMPO GRANDE | F16: Prospecto | G16: No contactado
A17: PASCUAL PAÍNO, JESÚS MANUEL | B17: VALLADOLID | C17: CAMPO GRANDE | D17: MEDIA | E17: 2 | F17: Prospecto | G17: No contactado
A18: SANTIAGO SASTRE, GENOVEVA | B18: VALLADOLID | C18: CAMPO GRANDE | D18: ALTA | E18: 2 | F18: Prospecto | G18: No contactado
A19: RODRÍGUEZ MARTÍN, Mª TERESA | B19: VALLADOLID | C19: CANTERAC | F19: Prospecto | G19: No contactado
A20: NAVAS MUÑOZ, AURORA | B20: VALLADOLID | C20: CANTERAC | D20: MEDIA | F20: Prospecto | G20: No contactado
A21: LLANES GARCÍA, LUIS MANUEL | B21: VALLADOLID | C21: CANTERAC | D21: MEDIA | E21: 46083 | F21: Prospecto | G21: No contactado
A22: GÓMEZ ARQUEROS, EDUARDO | B22: VALLADOLID | C22: CANTERAC | F22: Prospecto | G22: No contactado
A23: SECO DOMÍNGUEZ, Mª NIEVES | B23: VALLADOLID | C23: CANTERAC | F23: Prospecto | G23: No contactado
A24: BENÍTEZ VILLAR, BLANCA | B24: VALLADOLID | C24: CANTERAC | D24: ALTA | E24: 46114 | F24: Prospecto | G24: No contactado
A25: COUPEAU BORRÁS, PABLO JESÚS | B25: VALLADOLID | C25: CENTRO-GAMAZO | F25: Prospecto | G25: No contactado
A26: FUENTE MOREIRO, CONCEPCIÓN DE LA | B26: VALLADOLID | C26: CENTRO-GAMAZO | F26: Prospecto | G26: No contactado
A27: LÓPEZ-CASAMAYOR JUSTICIA, MARÍA DE LA PAZ | B27: VALLADOLID | C27: CENTRO-GAMAZO | F27: Prospecto | G27: No contactado
A28: PRESA VALENTÍN, VICENTE | B28: VALLADOLID | C28: CENTRO-GAMAZO | F28: Prospecto | G28: No contactado
A29: SOBRINO HEBRERO, CARMEN Mª | B29: VALLADOLID | C29: CENTRO-GAMAZO | F29: Prospecto | G29: No contactado
A30: ARROITA GARCÍA, FERNANDO | B30: VALLADOLID | C30: CENTRO-GAMAZO | F30: Prospecto | G30: No contactado
A31: CRESPO PÉREZ, JOSE LUIS | B31: VALLADOLID | C31: CENTRO-GAMAZO | D31: BAJA | E31: 46177 | F31: Prospecto | G31: No contactado
A32: GÓMEZ HERNÁNDEZ, ÁNGEL | B32: VALLADOLID | C32: CENTRO-GAMAZO | F32: Prospecto | G32: No contactado
A33: FURONES GIL, FRANCISCO JAVIER | B33: VALLADOLID | C33: CENTRO-GAMAZO | F33: Prospecto | G33: No contactado
A34: FERNÁNDEZ FERNÁNDEZ, VIRGINIA | B34: VALLADOLID | C34: CENTRO-GAMAZO | F34: Prospecto | G34: No contactado
A35: GARCÍA BLANCO, Mª ISABEL | B35: VALLADOLID | C35: CENTRO-GAMAZO | F35: Prospecto | G35: No contactado
A36: MARTÍNEZ DEL CASTILLO, JAVIER | B36: VALLADOLID | C36: CENTRO-GAMAZO | F36: Prospecto | G36: No contactado
A37: MARTÍNEZ MUÑOZ, MÓNICA | B37: VALLADOLID | C37: CENTRO-GAMAZO | F37: Prospecto | G37: No contactado
A38: ÁLVAREZ CARBALLO, SALVIA | B38: VALLADOLID | C38: CENTRO-GAMAZO | D38: ALTA | E38: 46114 | F38: Prospecto | G38: No contactado
A39: RODRÍGUEZ BALLESTERO, MARIA | B39: VALLADOLID | C39: CENTRO-GAMAZO | F39: Prospecto | G39: No contactado
A40: ARAUJO VALLE, MARTA | B40: VALLADOLID | C40: CENTRO-GAMAZO | D40: MEDIA | E40: 46083 | F40: Prospecto | G40: No contactado
A41: MÍNGUEZ IGLESIAS, ANA | B41: VALLADOLID | C41: CENTRO-GAMAZO | F41: Prospecto | G41: No contactado
A42: CANO GIL, SARA MARIA | B42: VALLADOLID | C42: CENTRO-GAMAZO | F42: Prospecto | G42: No contactado
A43: CALLEJA DÍEZ, PAULA | B43: VALLADOLID | C43: CENTRO-GAMAZO | F43: Prospecto | G43: No contactado
A44: PASTOR MANCISIDOR, CARMEN | B44: VALLADOLID | C44: CENTRO-GAMAZO | F44: Prospecto | G44: No contactado
A45: BENITO DEZA, Mª DEL PILAR DE | B45: VALLADOLID | C45: CENTRO-GAMAZO | D45: MEDIA | E45: 46114 | F45: Prospecto | G45: No contactado
A46: SANTAMARÍA VALDÉS, LORETO | B46: VALLADOLID | C46: CENTRO-GAMAZO | F46: Prospecto | G46: No contactado
A47: GARCÍA EVANGELIO, MARTA | B47: VALLADOLID | C47: CENTRO-GAMAZO | F47: Prospecto | G47: No contactado
A48: PRESA VALENTÍN, JUAN CARLOS | B48: VALLADOLID | C48: CENTRO-GAMAZO | F48: Prospecto | G48: No contactado
A49: ÁLVAREZ SÁNCHEZ, CÉSAR Mª | B49: VALLADOLID | C49: CIRCUNVALACION | F49: Prospecto | G49: No contactado
A50: TORANZO RODRÍGUEZ, ELENA | B50: VALLADOLID | C50: CIRCUNVALACIÓN | D50: ALTA | E50: 46083 | F50: Prospecto | G50: No contactado
A51: SANTOLINO GARCÍA, MARÍA ELENA | B51: VALLADOLID | C51: CIRCUNVALACIÓN | D51: ALTA | E51: 46115 | F51: Prospecto | G51: No contactado
A52: MOLPECERES GARCÍA DEL POZO, ISABEL | B52: VALLADOLID | C52: CIRCUNVALACION | F52: Prospecto | G52: No contactado
A53: COLINA RIVERA, PABLO | B53: VALLADOLID | C53: CIRCUNVALACION | F53: Prospecto | G53: No contactado
A54: LLANES GARCÍA, MARIA | B54: VALLADOLID | C54: CIRCUNVALACIÓN | F54: Prospecto | G54: No contactado
A55: TORANZO MORILLA, ANA MARGARITA | B55: VALLADOLID | C55: DELICIAS I | D55: ALTA | E55: 2 | F55: Prospecto | G55: No contactado
A56: MARTÍNEZ OLMEDO, RAFAEL | B56: VALLADOLID | C56: DELICIAS I | F56: Prospecto | G56: No contactado
A57: VILLAR VAQUERO, LUCÍA | B57: VALLADOLID | C57: DELICIAS I | D57: MEDIA | E57: 46083 | F57: Prospecto | G57: No contactado
A58: GARCÍA COLINO, Mª MAR | B58: VALLADOLID | C58: DELICIAS I | D58: BAJA | E58: 46083 | F58: Prospecto | G58: No contactado
A59: GARCÍA NOGUEIRAS, ALEJANDRO | B59: VALLADOLID | C59: DELICIAS I | D59: BAJA | F59: Prospecto | G59: No contactado
A60: PELETEIRO BENITO, ALICIA | B60: VALLADOLID | C60: DELICIAS I | F60: Prospecto | G60: No contactado
A61: ILLANA FERNÁNDEZ, BASILIA | B61: VALLADOLID | C61: DELICIAS I | F61: Prospecto | G61: No contactado
A62: SOBRINO MORENO, ÁLVARO | B62: VALLADOLID | C62: DELICIAS I | F62: Prospecto | G62: No contactado
A63: GÓMEZ MARTÍN, Mª JOSÉ | B63: VALLADOLID | C63: DELICIAS I | F63: Prospecto | G63: No contactado
A64: MELGAR TOBALINA, CÉSAR | B64: VALLADOLID | C64: DELICIAS II | D64: BAJA | E64: 46115 | F64: Prospecto | G64: No contactado
A65: SANJUÁN GONZÁLEZ, ANDREA INÉS | B65: VALLADOLID | C65: DELICIAS II | D65: MEDIA | F65: Prospecto | G65: No contactado
A66: CRESPO ALONSO, ISABEL ZAMORA CRESPO, FABRICIO MANUEL | B66: VALLADOLID | C66: DELICIAS II | D66: MEDIA | E66: 46054 | F66: Prospecto | G66: No contactado
A67: TEJERINA TOURIÑO, MARIA F. | B67: VALLADOLID | C67: DELICIAS II | D67: ALTA | E67: 2 | F67: Prospecto | G67: No contactado
A68: PLAZA PÉREZ, Mª DEL CARMEN | B68: VALLADOLID | C68: DELICIAS II | D68: MEDIA | E68: 46083 | F68: Prospecto | G68: No contactado
A69: AGUADO PASCUAL, CARMEN | B69: VALLADOLID | C69: DELICIAS II | F69: Prospecto | G69: No contactado
A70: CORONA SUANZES, TERESA GARCÍA CORONA, ROSARIO DE FÁTIMA GARCÍA CORONA, MARÍA | B70: VALLADOLID | C70: DELICIAS II | F70: Prospecto | G70: No contactado
A71: LARREA PRIETO, CRISTINA | B71: VALLADOLID | C71: DELICIAS II | F71: Prospecto | G71: No contactado
A72: CABRERA FERNÁNDEZ, ISABEL | B72: VALLADOLID | C72: DELICIAS II | F72: Prospecto | G72: No contactado
A73: SÁNCHEZ CONCELLÓN, RICARDO | B73: VALLADOLID | C73: ESPERANTO | F73: Prospecto | G73: No contactado
A74: JUNQUERA FLÓREZ, ANGEL JOSÉ | B74: VALLADOLID | C74: ESPERANTO | F74: Prospecto | G74: No contactado
A75: GÓMEZ VAAMONDE, ELENA GONZÁLEZ GÓMEZ, CARLOS | B75: VALLADOLID | C75: ESPERANTO | F75: Prospecto | G75: No contactado
A76: CHANA GALVÁN, Mª DEL CARMEN | B76: VALLADOLID | C76: ESPERANTO | F76: Prospecto | G76: No contactado
A77: GARCÍA CHICO, Mª LUISA | B77: VALLADOLID | C77: ESPERANTO | D77: ALTA | E77: 46115 | F77: Prospecto | G77: No contactado
A78: MARTÍN GONZÁLEZ, PAZ | B78: VALLADOLID | C78: ESPERANTO | F78: Prospecto | G78: No contactado
A79: LARRIBA CALLE, DIODORO | B79: VALLADOLID | C79: ESPERANTO | D79: BAJA | E79: 46177 | F79: Prospecto | G79: No contactado
A80: TASCÓN VICENTE, ANA BEATRIZ TASCÓN VICENTE, JAVIER | B80: VALLADOLID | C80: ESPERANTO | F80: Prospecto | G80: No contactado
A81: TORÍO ABAD, Mª ISABEL | B81: VALLADOLID | C81: ESPERANTO | D81: MEDIA | F81: Prospecto | G81: No contactado
A82: DIEGO GARCÍA, ARÁNZAZU | B82: VALLADOLID | C82: ESPERANTO | D82: MEDIA | E82: 46083 | F82: Prospecto | G82: No contactado
A83: PINDADO GONZÁLEZ, MARTA | B83: VALLADOLID | C83: HUERTA DEL REY | D83: MEDIA | E83: 0-1 | F83: Prospecto | G83: No contactado
A84: PÉREZ PEREIRA, JOSÉ ANTONIO BUIZA BADÁS, BEATRIZ | B84: VALLADOLID | C84: HUERTA DEL REY | F84: Prospecto | G84: No contactado
A85: MAROTO ARENAS, ESTHER FRAGUA LÁZARO, MARIA | B85: VALLADOLID | C85: HUERTA DEL REY | F85: Prospecto | G85: No contactado
A86: JIMÉNEZ GÓMEZ, VICENTE | B86: VALLADOLID | C86: HUERTA DEL REY | F86: Prospecto | G86: No contactado
A87: SÁNCHEZ MARTÍN, Mª ALMUDENA | B87: VALLADOLID | C87: HUERTA DEL REY | F87: Prospecto | G87: No contactado
A88: SENOVILLA SANCHO, JUAN CARLOS | B88: VALLADOLID | C88: HUERTA DEL REY | F88: Prospecto | G88: No contactado
A89: SÁNCHEZ-GIRÓN GONZÁLEZ, BEATRIZ | B89: VALLADOLID | C89: HUERTA DEL REY | E89: 46177 | F89: Prospecto | G89: No contactado
A90: ESTEBAN RODRÍGUEZ, Mª DEL MAR | B90: VALLADOLID | C90: HUERTA DEL REY | F90: Prospecto | G90: No contactado
A91: GUTIÉRREZ GARCÍA, ANTONIO JOSÉ | B91: VALLADOLID | C91: HUERTA DEL REY | D91: BAJA | E91: 46145 | F91: Prospecto | G91: No contactado
A92: NAVARRO GÓMEZ, JUAN ANTONIO | B92: VALLADOLID | C92: HUERTA DEL REY | F92: Prospecto | G92: No contactado
A93: LÓPEZ FRANCO, MIGUEL ÁNGEL | B93: VALLADOLID | C93: LA VICTORIA | F93: Prospecto | G93: No contactado
A94: CANO BORREGO, JUAN ANDRES | B94: VALLADOLID | C94: LA VICTORIA | F94: Prospecto | G94: No contactado
A95: RUIZ HORTELANO, MIGUEL ANGEL | B95: VALLADOLID | C95: LA VICTORIA | E95: 46083 | F95: Prospecto | G95: No contactado
A96: SANTOS ESCUDERO, BEATRIZ | B96: VALLADOLID | C96: LA VICTORIA | F96: Prospecto | G96: No contactado
A97: GARCÍA QUEIPO, ANA | B97: VALLADOLID | C97: LA VICTORIA | D97: ALTA | E97: 46083 | F97: Prospecto | G97: No contactado
A98: ALAGUERO CALERO, SARA | B98: VALLADOLID | C98: LA VICTORIA | F98: Prospecto | G98: No contactado
A99: PÉREZ RODRÍGUEZ, Mª MERCEDES | B99: VALLADOLID | C99: LA VICTORIA | D99: MEDIA | E99: 46083 | F99: Prospecto | G99: No contactado
A100: MARTÍN VIADA, JOSÉ RODRIGO | B100: VALLADOLID | C100: MAGDALENA | D100: MEDIA | E100: 46115 | F100: Prospecto | G100: No contactado
...

Sheet Reuniones
A1: Farmacia | B1: Tipo | C1: Fecha | D1: Resultado | E1: Objeción | F1: Motivo positivo | G1: Resumen | H1: Próxima acción

Sheet Auditorias
A1: Farmacia | B1: Estado | C1: Resultado | D1: Fecha venta | E1: Fecha entrega | F1: Horas totales

Sheet Clientes
A1: Farmacia | B1: Tipo servicio | C1: Fecha inicio | D1: Estado | E1: Cuota mensual (€) | F1: Último contacto | G1: Motivo baja

Sheet Dashboard
A1: CRM FARMACIAS — DASHBOARD COMERCIAL
A3: Indicador | B3: Valor | C3: Lectura | E3: Provincia | F3: Total
A4: Farmacias totales | B4: =COUNTA(Farmacias!A2:A600) -> 316 | C4: Base comercial cargada | E4: Valladolid | F4: =COUNTIF(Farmacias!B2:B600,"Valladolid") -> 278
A5: Contactadas | B5: =COUNTIF(Farmacias!F2:F600,"Contactada") -> 0 | C5: Primer contacto realizado | E5: Palencia | F5: =COUNTIF(Farmacias!B2:B600,"Palencia") -> 38
A6: Reuniones | B6: =COUNTIF(Farmacias!F2:F600,"Reunión") -> 0 | C6: Interés cualificado | E6: Salamanca | F6: =COUNTIF(Farmacias!B2:B600,"Salamanca") -> 0
A7: Auditorías | B7: =COUNTIF(Farmacias!F2:F600,"Auditoría") -> 0 | C7: Oportunidad avanzada
A8: Propuestas | B8: =COUNTIF(Farmacias!F2:F600,"Propuesta enviada") -> 0 | C8: Oferta enviada
A9: Clientes activos | B9: =COUNTIF(Farmacias!F2:F600,"Cliente activo") -> 0 | C9: MRR real | E9: Prioridad | F9: Total
A10: MRR estimado ponderado | B10: =SUM(Farmacias!U2:U600) -> 0 | C10: Forecast ponderado | E10: ALTA | F10: =COUNTIF(Farmacias!D2:D600,"ALTA") -> 23
A11: Tasa reunión/contacto | B11: =IFERROR(B4/B3,0) -> 0 | C11: Conversión inicial | E11: MEDIA | F11: =COUNTIF(Farmacias!D2:D600,"MEDIA") -> 46
A12: Tasa cliente/auditoría | B12: =IFERROR(B7/B5,0) -> 0 | C12: Conversión final | E12: BAJA | F12: =COUNTIF(Farmacias!D2:D600,"BAJA") -> 44
E13: Sin definir | F13: =COUNTBLANK(Farmacias!D2:D600) -> 486
A15: Fase | B15: Nº farmacias | C15: % sobre total
A16: Prospecto | B16: =COUNTIF(Farmacias!F2:F600,"Prospecto") -> 316 | C16: =IFERROR(B16/$B$4,0) -> 1 | E16: Próxima acción | F16: Total
A17: Contactada | B17: =COUNTIF(Farmacias!F2:F600,"Contactada") -> 0 | C17: =IFERROR(B17/$B$4,0) -> 0 | E17: Visitar | F17: =COUNTIF(Farmacias!AA2:AA600,"Visitar") -> 0
A18: Reunión | B18: =COUNTIF(Farmacias!F2:F600,"Reunión") -> 0 | C18: =IFERROR(B18/$B$4,0) -> 0 | E18: Seguimiento | F18: =COUNTIF(Farmacias!AA2:AA600,"Seguimiento") -> 0
A19: Auditoría | B19: =COUNTIF(Farmacias!F2:F600,"Auditoría") -> 0 | C19: =IFERROR(B19/$B$4,0) -> 0 | E19: Programada | F19: =COUNTIF(Farmacias!AA2:AA600,"Programada") -> 0
A20: Propuesta enviada | B20: =COUNTIF(Farmacias!F2:F600,"Propuesta enviada") -> 0 | C20: =IFERROR(B20/$B$4,0) -> 0 | E20: Mantenimiento | F20: =COUNTIF(Farmacias!AA2:AA600,"Mantenimiento") -> 0
A21: Cliente activo | B21: =COUNTIF(Farmacias!F2:F600,"Cliente activo") -> 0 | C21: =IFERROR(B21/$B$4,0) -> 0
A22: Perdido | B22: =COUNTIF(Farmacias!F2:F600,"Perdido") -> 0 | C22: =IFERROR(B22/$B$4,0) -> 0
